build_with_cython/__init__.py
build_with_cython/backend.py
build_with_cython/cbuild.py
build_with_cython/dep_an.py
build_with_cython-0.0.3.dist-info/METADATA
build_with_cython-0.0.3.dist-info/WHEEL
build_with_cython-0.0.3.dist-info/entry_points.txt
build_with_cython-0.0.3.dist-info/top_level.txt
build_with_cython-0.0.3.dist-info/RECORD
